superinference/__init__.py
superinference/devto.py
superinference/github.py
superinference-1.0.9.dist-info/LICENSE.txt
superinference-1.0.9.dist-info/METADATA
superinference-1.0.9.dist-info/WHEEL
superinference-1.0.9.dist-info/top_level.txt
superinference-1.0.9.dist-info/RECORD
