Metadata-Version: 2.1
Name: superinference
Version: 1.0.9
Summary: Superinference is a library that infers analysis-ready attributes from a person''s social media username or unique identifier and returns them as JSON objects.
Author: Timotius Marselo
Author-email: timotiusmarselo@gmail.com
License-File: LICENSE.txt
